setup.cfg
setup.py
flaskbox/__init__.py
flaskbox/__main__.py
flaskbox/app.py
flaskbox/config.py
flaskbox/constants.py
flaskbox/fake_data.py
flaskbox/generators.py
flaskbox/helpers.py
flaskbox/reader.py
flaskbox/reader_helper.py
flaskbox.egg-info/PKG-INFO
flaskbox.egg-info/SOURCES.txt
flaskbox.egg-info/dependency_links.txt
flaskbox.egg-info/requires.txt
flaskbox.egg-info/top_level.txt