Metadata-Version: 1.1
Name: flaskbox
Version: 0.1.1
Summary: Easy and fast tool for mock an API, with a fake data
Home-page: https://github.com/MichaelYusko/Flaskbox
Author: Michael Yusko
Author-email: freshjelly12@yahoo.com
License: UNKNOWN
Platform: UNKNOWN
Classifier: Development Status :: 1 - Planning
Classifier: Environment :: Console
Classifier: Programming Language :: Python :: 3.5
Classifier: Programming Language :: Python :: 3.6
Classifier: License :: OSI Approved :: MIT License
